wikidata_dl/__about__.py
wikidata_dl/__init__.py
wikidata_dl/cli.py
wikidata_dl/vocabulary.py
wikidata_dl/wikidata.py
wikidata_dl-2023.7.27.dist-info/METADATA
wikidata_dl-2023.7.27.dist-info/WHEEL
wikidata_dl-2023.7.27.dist-info/entry_points.txt
wikidata_dl-2023.7.27.dist-info/licenses/LICENSE
wikidata_dl-2023.7.27.dist-info/RECORD
