Metadata-Version: 2.1
Name: wikidata-dl
Version: 2023.7.27
Summary: Download data from Wikidata based on input SPARQL query.
Project-URL: Documentation, https://github.com/yaph/wikidata-dl#readme
Project-URL: Issues, https://github.com/yaph/wikidata-dl/issues
Project-URL: Source, https://github.com/yaph/wikidata-dl
Author-email: Ramiro Gómez <code@ramiro.org>
License-Expression: MIT
License-File: LICENSE
Keywords: cli,command line,dl,download,sparql,wikidata
Classifier: Development Status :: 4 - Beta
Classifier: Intended Audience :: Developers
Classifier: Intended Audience :: Science/Research
Classifier: License :: OSI Approved :: MIT License
Classifier: Programming Language :: Python
Classifier: Programming Language :: Python :: 3.9
Classifier: Programming Language :: Python :: 3.10
Classifier: Programming Language :: Python :: 3.11
Classifier: Programming Language :: Python :: Implementation :: CPython
Classifier: Programming Language :: Python :: Implementation :: PyPy
Requires-Python: >=3.9
Requires-Dist: httpx
Requires-Dist: python-dateutil
Requires-Dist: wptools
